{
    "date": "2024-11-11 10:42:20.000290",
    "defines": [
        "FMT_SHARED",
        "GTEST_LINKED_AS_SHARED_LIBRARY=1",
        "BOOST_ALL_NO_LIB",
        "BOOST_STACKTRACE_USE_NOOP",
        "BOOST_STACKTRACE_USE_WINDBG",
        "BOOST_STACKTRACE_USE_WINDBG_CACHED",
        "STB_TEXTEDIT_KEYTYPE=unsigned"
    ],
    "packages": {
        "b2/5.2.1": {
            "binDir": "C:\\Temp\\conan2\\p\\b2c45ac73ef9f80\\p\\bin",
            "includeDir": "",
            "libDir": ""
        },
        "boost/1.86.0": {
            "binDir": "C:\\Temp\\conan2\\p\\b\\boost457804dd335df\\p\\bin",
            "includeDir": "C:\\Temp\\conan2\\p\\b\\boost457804dd335df\\p\\include",
            "libDir": "C:\\Temp\\conan2\\p\\b\\boost457804dd335df\\p\\lib"
        },
        "bullet3/3.25": {
            "binDir": "C:\\Temp\\conan2\\p\\b\\bulle424d9c995feb3\\p\\bin",
            "includeDir": "C:\\Temp\\conan2\\p\\b\\bulle424d9c995feb3\\p\\include\\bullet",
            "libDir": "C:\\Temp\\conan2\\p\\b\\bulle424d9c995feb3\\p\\lib"
        },
        "bzip2/1.0.8": {
            "binDir": "C:\\Temp\\conan2\\p\\b\\bzip29b6c7d9d87822\\p\\bin",
            "includeDir": "C:\\Temp\\conan2\\p\\b\\bzip29b6c7d9d87822\\p\\include",
            "libDir": "C:\\Temp\\conan2\\p\\b\\bzip29b6c7d9d87822\\p\\lib"
        },
        "cmake/3.30.5": {
            "binDir": "C:\\Temp\\conan2\\p\\cmakefb3b433358da1\\p\\bin",
            "includeDir": "",
            "libDir": ""
        },
        "fmt/11.0.2": {
            "binDir": "C:\\Temp\\conan2\\p\\b\\fmtccb3a44f7d832\\p\\bin",
            "includeDir": "C:\\Temp\\conan2\\p\\b\\fmtccb3a44f7d832\\p\\include",
            "libDir": "C:\\Temp\\conan2\\p\\b\\fmtccb3a44f7d832\\p\\lib"
        },
        "glad/0.1.36": {
            "binDir": "C:\\Temp\\conan2\\p\\b\\glad2a77b4248d865\\p\\bin",
            "includeDir": "C:\\Temp\\conan2\\p\\b\\glad2a77b4248d865\\p\\include",
            "libDir": "C:\\Temp\\conan2\\p\\b\\glad2a77b4248d865\\p\\lib"
        },
        "glm/cci.20230113": {
            "binDir": "",
            "includeDir": "C:\\Temp\\conan2\\p\\glmdf97922a12435\\p\\include",
            "libDir": ""
        },
        "gtest/1.15.0": {
            "binDir": "C:\\Temp\\conan2\\p\\b\\gtest5e872d8f15f2b\\p\\bin",
            "includeDir": "C:\\Temp\\conan2\\p\\b\\gtest5e872d8f15f2b\\p\\include",
            "libDir": "C:\\Temp\\conan2\\p\\b\\gtest5e872d8f15f2b\\p\\lib"
        },
        "inja/3.4.0": {
            "binDir": "",
            "includeDir": "C:\\Temp\\conan2\\p\\inja62ccb399ee74d\\p\\include",
            "libDir": ""
        },
        "lz4/1.10.0": {
            "binDir": "C:\\Temp\\conan2\\p\\b\\lz4fa8eb86bcabbd\\p\\bin",
            "includeDir": "C:\\Temp\\conan2\\p\\b\\lz4fa8eb86bcabbd\\p\\include",
            "libDir": "C:\\Temp\\conan2\\p\\b\\lz4fa8eb86bcabbd\\p\\lib"
        },
        "magic_enum/0.9.6": {
            "binDir": "",
            "includeDir": "C:\\Temp\\conan2\\p\\magic056426a1202a6\\p\\include",
            "libDir": ""
        },
        "nasm/2.16.01": {
            "binDir": "C:\\Temp\\conan2\\p\\nasm82fc2c9a305c1\\p\\bin",
            "includeDir": "",
            "libDir": ""
        },
        "nlohmann_json/3.11.3": {
            "binDir": "",
            "includeDir": "C:\\Temp\\conan2\\p\\nlohm0567ffc90cfc1\\p\\include",
            "libDir": ""
        },
        "openssl/1.1.1w": {
            "binDir": "C:\\Temp\\conan2\\p\\b\\opensb889ef5f9443d\\p\\bin",
            "includeDir": "C:\\Temp\\conan2\\p\\b\\opensb889ef5f9443d\\p\\include",
            "libDir": "C:\\Temp\\conan2\\p\\b\\opensb889ef5f9443d\\p\\lib"
        },
        "rapidjson/cci.20220822": {
            "binDir": "",
            "includeDir": "C:\\Temp\\conan2\\p\\rapideb2d90c50e7f7\\p\\include",
            "libDir": ""
        },
        "sdl/2.30.6": {
            "binDir": "C:\\Temp\\conan2\\p\\b\\sdl6e535e047d965\\p\\bin",
            "includeDir": "C:\\Temp\\conan2\\p\\b\\sdl6e535e047d965\\p\\include\\SDL2",
            "libDir": "C:\\Temp\\conan2\\p\\b\\sdl6e535e047d965\\p\\lib"
        },
        "stb/cci.20240531": {
            "binDir": "",
            "includeDir": "C:\\Temp\\conan2\\p\\stb19b77fb56ffd7\\p\\include",
            "libDir": ""
        },
        "strawberryperl/5.32.1.1": {
            "binDir": "C:\\Temp\\conan2\\p\\straw898fb56546adc\\p\\bin",
            "includeDir": "",
            "libDir": ""
        },
        "zlib/1.3.1": {
            "binDir": "C:\\Temp\\conan2\\p\\b\\zliba3bef5f6359a4\\p\\bin",
            "includeDir": "C:\\Temp\\conan2\\p\\b\\zliba3bef5f6359a4\\p\\include",
            "libDir": "C:\\Temp\\conan2\\p\\b\\zliba3bef5f6359a4\\p\\lib"
        }
    }
}