<?xml version="1.0" encoding="utf-8"?>
<!-- модель игрового движка -->
<!-- временный комментарий version 0.5 -->
<model name="Королевский тигр" >
  <part name="Hull">
    <state>
      <hierarchy>
        <joint>
          <node name="Hull">
            <position x="0" y="0" z="0"/>
            <scale    x="1" y="1" z="1"/>
            <rotate   x="1" y="0" z="0" a="0"/>
          </node>
          <constraint type="polar" r0="0" r1="0" a0="0" a1="0" b0="0" b1="0">
            <A x="0" y="0" z="0"/>
            <B x="0" y="0" z="0"/>
            <spring>
              <>
              <>
            </spring>
          </constraint>
          <constraint type="cartesian" x0="0" x1="0" y0="0" y1="0" z0="0" z1="0">
            <A x="0" y="0" z="0"/>
            <B x="0" y="0" z="0"/>
          </constraint>
        </joint>
        <joint>
          <node name="Turret">
            <position x="-0.010775" y="-0.079083003" z="0.98732799"/>
            <scale    x="1" y="1" z="1"/>
            <rotate   x="1" y="0" z="0" a="0"/>
          </node>
          <property>
          </property>
        </joint>
        <joint>
          <node name="TrackL">
            <position x="0"  y="0" z="-1.0800000"/>
            <scale    x="-1" y="-1" z="1"/>
            <rotate   x="1"  y="0" z="0" a="0"/>
          </node>
          <property>
          </property>
        </joint>
        <joint>
          <node name="TrackR">
            <position x="0"  y="0" z="-1.0800000"/>
            <scale    x="-1" y="-1" z="1"/>
            <rotate   x="1"  y="0" z="0" a="0"/>
          </node>
          <property>
          </property>
        </joint>
        <joint>
          <node name="ChassisL">
            <position x="0"  y="0" z="-1.0800000"/>
            <scale    x="-1" y="-1" z="1"/>
            <rotate   x="1"  y="0" z="0" a="0"/>
          </node>
          <property>
          </property>
        </joint>
        <joint>
          <node name="ChassisR">
            <position x="0"  y="0" z="-1.0800000"/>
            <scale    x="-1" y="-1" z="1"/>
            <rotate   x="1"  y="0" z="0" a="0"/>
          </node>
          <property>
          </property>
        </joint>
      </hierarchy>
      <graphic>
        <shape path="../../Graphic/models/KingTiger/Hull.mesh"/>
      </graphic>
      <physic>
        <shape path="../../Physic/models/KingTiger/Hull.mesh"/>
        <property>
            <mass value="30000" x="0" y="0" z="0" />
        </property>
      </physic>
    </state>
  </part>
  <part name="Turret">
    <state>
      <hierarchy>
        <joint>
          <node name="Gun">
            <position x="0.064711" y="1.421399" z="0.367343"/>
            <scale    x="-1"       y="-1"       z="1"/>
            <rotate   x="1"        y="0"        z="0" a="0"/>
          </node>
          <property>
          </property>
        </joint>
      </hierarchy>
      <graphic>
        <shape path="../../Graphic/models/KingTiger/Turret.mesh"/>
      </graphic>
      <physic>
        <shape path="../../Physic/models/KingTiger/Turret.mesh"/>
        <property>
        </property>
      </physic>
    </state>
  </part>
  <part name="TrackL">
    <state>
      <graphic>
        <shape path="../../Graphic/models/KingTiger/TrackL.mesh"/>
      </graphic>
      <physic>
        <shape path="../../Physic/models/KingTiger/TrackL.mesh"/>
        <property>
        </property>
      </physic>
    </state>
  </part>
  <part name="TrackR">
    <state>
      <graphic>
        <shape path="../../Graphic/models/KingTiger/TrackR.mesh"/>
      </graphic>
      <physic>
        <shape path="../../Physic/models/KingTiger/TrackR.mesh"/>
        <property>
        </property>
      </physic>
    </state>
  </part>
  <part name="ChassisL">
    <state>
      <graphic>
        <shape path="../../Graphic/models/KingTiger/ChassisL.mesh"/>
      </graphic>
      <physic>
        <shape path="../../Physic/models/KingTiger/ChassisL.mesh"/>
        <property>
        </property>
      </physic>
    </state>
  </part>
  <part name="ChassisR">
    <state>
      <graphic>
        <shape path="../../Graphic/models/KingTiger/ChassisR.mesh"/>
      </graphic>
      <physic>
        <shape path="../../Physic/models/KingTiger/ChassisR.mesh"/>
        <property>
        </property>
      </physic>
    </state>
  </part>
  <part name="Gun">
    <state>
      <graphic>
        <shape path="../../Graphic/models/KingTiger/Gun.mesh"/>
      </graphic>
      <physic>
        <shape path="../../Physic/models/KingTiger/Gun.mesh"/>
        <property>
        </property>
      </physic>
    </state>
  </part>
</model>