{
    "targetForParsing": {
        "directories": [
            "."
        ],
        "recursive": true
    },
    "filter": {
        "attribute": "",
        "extensions": [
            ".h",
            ".hpp",
            ".hh",
            ".hxx",
            ".h++"
        ],
        "inheritance": "nsECSFramework::IComponent"
    },
    "targetForCodeGeneration": {
        "directory": "./Generated files",
        "includeListFileName": "ComponentIncludeList",
        "header": "\tReflectionCodeGenerator",
        "typeCustomizerMap": {},
        "appendTypeCustomizerMap": true,
        "implementations": {
            "JsonSerializerGenerator": {
                "exportDeclaration": "DllExport",
                "nameSpaceName": "nsTornadoEngine",
                "fileName": "ComponentJsonSerializer",
                "className": "TComponentJsonSerializer",
                "keyValueMap": {}
            },
            "TypeInformationGenerator": {
                "exportDeclaration": "DllExport",
                "nameSpaceName": "nsTornadoEngine",
                "fileName": "ComponentTypeInformation",
                "className": "TComponentTypeInformation",
                "keyValueMap": {}
            },
            "EntityManagerExtension": {
                "exportDeclaration": "DllExport",
                "nameSpaceName": "nsTornadoEngine",
                "fileName": "ComponentEntityManagerExtension",
                "className": "TComponentEntityManagerExtension",
                "keyValueMap": {
                    "entityManagerHeaderPath": "ECS/include/EntityManager.h"
                }
            }
        }
    }
}